one_cycle_lr/__init__.py
one_cycle_lr/lr_finder.py
one_cycle_lr/one_cycle_scheduler.py
one_cycle_lr/param_scheduler.py
keras_one_cycle_lr-0.0.1.dist-info/LICENSE
keras_one_cycle_lr-0.0.1.dist-info/METADATA
keras_one_cycle_lr-0.0.1.dist-info/WHEEL
keras_one_cycle_lr-0.0.1.dist-info/top_level.txt
keras_one_cycle_lr-0.0.1.dist-info/RECORD
