Metadata-Version: 2.1
Name: keras-one-cycle-lr
Version: 0.0.1
Summary: Keras implementation of One Cycle Policy and LR Finder
Home-page: https://github.com/shivam-agarwal-17/Keras-training-tools
Author: Shivam Agarwal
Author-email: shivam.agarwal151@gmail.com
License: UNKNOWN
Platform: UNKNOWN
Classifier: Programming Language :: Python :: 3
Classifier: License :: OSI Approved :: MIT License
Classifier: Operating System :: OS Independent
